__init_.py
ai_utils.py
article_generator.py
config_parser.py
git_utils.py
gitscribeai-1.0.1.dist-info/licenses/LICENSE
gitscribeai-1.0.1.dist-info/METADATA
gitscribeai-1.0.1.dist-info/WHEEL
gitscribeai-1.0.1.dist-info/entry_points.txt
gitscribeai-1.0.1.dist-info/top_level.txt
gitscribeai-1.0.1.dist-info/RECORD
