Metadata-Version: 2.4
Name: GitScribeAI
Version: 1.0.1
Summary: A tool to analyze Git commits and generate articles.
Author-email: Michael Trimarchi <michael@amarulasolutions.com>
License: The MIT License
Project-URL: homepage, https://github.com/amarula/git-analyzer
Requires-Python: >=3.8
License-File: LICENSE
Requires-Dist: GitPython==3.1.44
Requires-Dist: markdown_strings==v3.4.0
Requires-Dist: langchain-openai==0.3.34
Dynamic: license-file
